pyethnobiology/__init__.py
pyethnobiology/indices.py
pyethnobiology/pyethnobiology.py
pyethnobiology/stats.py
pyethnobiology/visualization.py
pyethnobiology-0.1.1.dist-info/LICENSE
pyethnobiology-0.1.1.dist-info/METADATA
pyethnobiology-0.1.1.dist-info/WHEEL
pyethnobiology-0.1.1.dist-info/RECORD
