Metadata-Version: 2.1
Name: pyethnobiology
Version: 0.1.1
Summary: Ethnobiological data assessment tool.
License: MIT
Author: Ogün Demir
Author-email: ogundemir8@gmail.com
Requires-Python: >=3.10,<4.0
Classifier: Development Status :: 5 - Production/Stable
Classifier: Intended Audience :: Developers
Classifier: License :: OSI Approved :: MIT License
Classifier: Operating System :: OS Independent
Classifier: Programming Language :: Python :: 3
Classifier: Programming Language :: Python :: 3.10
Classifier: Programming Language :: Python :: 3.11
Classifier: Programming Language :: Python :: 3.12
Classifier: Topic :: Software Development :: Libraries :: Python Modules
Requires-Dist: Pillow (==10.1.0)
Requires-Dist: biopython (==1.81)
Requires-Dist: contourpy (==1.2.0)
Requires-Dist: cycler (==0.12.1)
Requires-Dist: fonttools (==4.47.0)
Requires-Dist: importlib-resources (==6.1.1)
Requires-Dist: joblib (==1.3.2)
Requires-Dist: kiwisolver (==1.4.5)
Requires-Dist: matplotlib (==3.8.2)
Requires-Dist: numpy (==1.26.2)
Requires-Dist: openpyxl (==3.1.2)
Requires-Dist: packaging (==23.2)
Requires-Dist: pandas (==2.1.4)
Requires-Dist: pyCirclize (==1.1.0)
Requires-Dist: pyparsing (==3.1.1)
Requires-Dist: python-dateutil (==2.8.2)
Requires-Dist: pytz (==2023.3.post1)
Requires-Dist: rdata (==0.10.0)
Requires-Dist: scikit-learn (==1.3.2)
Requires-Dist: scipy (==1.11.4)
Requires-Dist: seaborn (==0.13.0)
Requires-Dist: six (==1.16.0)
Requires-Dist: threadpoolctl (==3.2.0)
Requires-Dist: tzdata (==2023.3)
Requires-Dist: xarray (==2023.12.0)
Requires-Dist: zipp (==3.17.0)
Project-URL: documentation, https://github.com/demirogun/pyethnobiology/blob/main/README.md
Project-URL: github, https://github.com/demirogun/pyethnobiology
Project-URL: homepage, https://github.com/demirogun/pyethnobiology
Project-URL: issues, https://github.com/demirogun/pyethnobiology/issues
Project-URL: repository, https://pypi.org/project/pyethnobiology/
